pyeitaa/__init__.py
pyeitaa/client.py
pyeitaa/mime_types.py
pyeitaa/utils.py
pyeitaa/connection/__init__.py
pyeitaa/connection/transport.py
pyeitaa/enums/__init__.py
pyeitaa/enums/auto_name.py
pyeitaa/enums/next_code_type.py
pyeitaa/enums/parse_mode.py
pyeitaa/enums/sent_code_type.py
pyeitaa/enums/user_status.py
pyeitaa/errors/__init__.py
pyeitaa/errors/rpc_error.py
pyeitaa/errors/exceptions/__init__.py
pyeitaa/errors/exceptions/all.py
pyeitaa/errors/exceptions/bad_request_400.py
pyeitaa/errors/exceptions/flood_420.py
pyeitaa/errors/exceptions/forbidden_403.py
pyeitaa/errors/exceptions/internal_server_error_500.py
pyeitaa/errors/exceptions/not_acceptable_406.py
pyeitaa/errors/exceptions/see_other_303.py
pyeitaa/errors/exceptions/unauthorized_401.py
pyeitaa/methods/__init__.py
pyeitaa/methods/auth/__init__.py
pyeitaa/methods/auth/send_code.py
pyeitaa/methods/auth/sign_in.py
pyeitaa/methods/core/__init__.py
pyeitaa/methods/core/invoke.py
pyeitaa/methods/core/save_file.py
pyeitaa/methods/users/__init__.py
pyeitaa/methods/users/get_me.py
pyeitaa/methods/utils/__init__.py
pyeitaa/methods/utils/start.py
pyeitaa/methods/utils/stop.py
pyeitaa/raw/__init__.py
pyeitaa/raw/all.py
pyeitaa/raw/base/__init__.py
pyeitaa/raw/base/access_point_rule.py
pyeitaa/raw/base/account_days_ttl.py
pyeitaa/raw/base/ads_click_action.py
pyeitaa/raw/base/ads_location.py
pyeitaa/raw/base/authorization.py
pyeitaa/raw/base/auto_download_settings.py
pyeitaa/raw/base/bad_msg_notification.py
pyeitaa/raw/base/bank_card_open_url.py
pyeitaa/raw/base/base_theme.py
pyeitaa/raw/base/bind_auth_key_inner.py
pyeitaa/raw/base/bot_command.py
pyeitaa/raw/base/bot_command_scope.py
pyeitaa/raw/base/bot_info.py
pyeitaa/raw/base/bot_inline_message.py
pyeitaa/raw/base/bot_inline_result.py
pyeitaa/raw/base/cdn_config.py
pyeitaa/raw/base/cdn_public_key.py
pyeitaa/raw/base/channel_admin_log_event.py
pyeitaa/raw/base/channel_admin_log_event_action.py
pyeitaa/raw/base/channel_admin_log_events_filter.py
pyeitaa-0.1.1.dist-info/licenses/LICENSE
pyeitaa-0.1.1.dist-info/METADATA
pyeitaa-0.1.1.dist-info/WHEEL
pyeitaa-0.1.1.dist-info/top_level.txt
pyeitaa-0.1.1.dist-info/RECORD
