Metadata-Version: 2.4
Name: pyeitaa
Version: 0.1.1
Summary: Elegant, modern and asynchronous Eitaa MTProto API framework in Python for users.
Author-email: MSDanesh <msdanesh48@gmail.com>
License-Expression: Apache-2.0
Project-URL: Homepage, https://github.com/MSDanesh/pyeitaa
Project-URL: Repository, https://github.com/MSDanesh/pyeitaa
Project-URL: Issues, https://github.com/MSDanesh/pyeitaa/issues
Keywords: eitaa,pyeitaa,chat,messenger,mtproto,api,client,library,python
Classifier: Programming Language :: Python :: 3
Classifier: Programming Language :: Python :: 3.10
Classifier: Operating System :: OS Independent
Classifier: Development Status :: 3 - Alpha
Classifier: Intended Audience :: Developers
Classifier: Topic :: Software Development :: Libraries
Requires-Python: >=3.10
License-File: LICENSE
Requires-Dist: aiohttp
Requires-Dist: base36
Dynamic: license-file
